README.md
setup.cfg
setup.py
fastapi_quickstart/__init__.py
fastapi_quickstart/auth.py
fastapi_quickstart/crud.py
fastapi_quickstart/datatypes.py
fastapi_quickstart/db.py
fastapi_quickstart.egg-info/PKG-INFO
fastapi_quickstart.egg-info/SOURCES.txt
fastapi_quickstart.egg-info/dependency_links.txt
fastapi_quickstart.egg-info/requires.txt
fastapi_quickstart.egg-info/top_level.txt