Metadata-Version: 1.1
Name: fastapi-quickstart
Version: 0.3
Summary: Common Helper functions which gets you kickstart with your fastapi development.
Home-page: https://www.lokendrabohra.tech
Author: Lokendra Bairwa
Author-email: lokendrabairwa@gmail.com
License: UNKNOWN
Download-URL: https://github.com/lokendra1704/fastapi_quickstart/archive/v_03.tar.gz
Platform: UNKNOWN
